hola_nbdev2/__init__.py
hola_nbdev2/_nbdev.py
hola_nbdev2/core.py
nbdev_whatsapp/__init__.py
nbdev_whatsapp/_nbdev.py
nbdev_whatsapp/core.py
nbdev_whatsapp-0.0.1.dist-info/LICENSE
nbdev_whatsapp-0.0.1.dist-info/METADATA
nbdev_whatsapp-0.0.1.dist-info/WHEEL
nbdev_whatsapp-0.0.1.dist-info/entry_points.txt
nbdev_whatsapp-0.0.1.dist-info/top_level.txt
nbdev_whatsapp-0.0.1.dist-info/RECORD
