Metadata-Version: 2.1
Name: nbdev-whatsapp
Version: 0.0.1
Summary: Tutorial nbdev
Home-page: https://github.com/arlingva/nbdev_whatsapp/tree/master/
Author: Arling Vázquez
Author-email: arling.vazquez@gmail.com
License: Apache Software License 2.0
Keywords: tutorial nbdev
Platform: UNKNOWN
Classifier: Development Status :: 3 - Alpha
Classifier: Intended Audience :: Developers
Classifier: License :: OSI Approved :: Apache Software License
Classifier: Natural Language :: English
Classifier: Programming Language :: Python :: 3.6
Classifier: Programming Language :: Python :: 3.7
Classifier: Programming Language :: Python :: 3.8
Requires-Python: >=3.6
